hycli/__init__.py
hycli/cli.py
hycli/commands/__init__.py
hycli/commands/callbacks.py
hycli/commands/context_default.py
hycli/commands/to_csv.py
hycli/commands/to_json.py
hycli/commands/to_xlsx.py
hycli/commands/types.py
hycli/commons/auth.py
hycli/commons/calculate_improvements.py
hycli/commons/consts.py
hycli/commons/error_handling.py
hycli/commons/excel_adapter.py
hycli/commons/jobs.py
hycli/commons/model_comparer.py
hycli/commons/request.py
hycli/commons/structure.py
hycli/compare.py
hycli/convert/csv.py
hycli/convert/json.py
hycli/convert/xlsx.py
hycli/evaluate.py
hycli/evaluation/__init__.py
hycli/evaluation/error_analysis.py
hycli/evaluation/evaluation.py
hycli/extract.py
hycli-0.6.0.dist-info/entry_points.txt
hycli-0.6.0.dist-info/WHEEL
hycli-0.6.0.dist-info/METADATA
hycli-0.6.0.dist-info/RECORD
