Metadata-Version: 2.1
Name: hycli
Version: 0.6.0
Summary: Hypatos cli tool to batch extract documents through the API and to compare the results.
Home-page: https://hypatos.ai
Keywords: hypatos,document,etraction,ocr
Author: Dylan Bartels
Author-email: dylan.bartels@hypatos.ai
Requires-Python: >=3.7,<4.0
Classifier: Programming Language :: Python :: 3
Classifier: Programming Language :: Python :: 3.7
Classifier: Programming Language :: Python :: 3.8
Requires-Dist: Jinja2 (>=2.11.2,<3.0.0)
Requires-Dist: Pillow (>=8.1.0,<9.0.0)
Requires-Dist: XlsxWriter (>=1.2.7,<2.0.0)
Requires-Dist: click (>=7.0,<8.0)
Requires-Dist: click-log (>=0.3.2,<0.4.0)
Requires-Dist: filetype (>=1.0.5,<2.0.0)
Requires-Dist: fpdf (>=1.7.2,<2.0.0)
Requires-Dist: halo (>=0.0.29,<0.0.32)
Requires-Dist: openpyxl (>=3.0.5,<4.0.0)
Requires-Dist: pandas (>=1.0.5,<2.0.0)
Requires-Dist: pdf2image (>=1.14.0,<2.0.0)
Requires-Dist: requests (>=2.22.0,<3.0.0)
Requires-Dist: seaborn (>=0.11.1,<0.12.0)
Requires-Dist: sqlalchemy (>=1.3.22,<2.0.0)
Requires-Dist: xlrd (>=1.2.0,<2.0.0)
Project-URL: Documentation, https://hypatos.github.io/hycli/
